flask_sanitize_escape/__init__.py
flask_sanitize_escape-0.0.3.dist-info/LICENSE
flask_sanitize_escape-0.0.3.dist-info/METADATA
flask_sanitize_escape-0.0.3.dist-info/WHEEL
flask_sanitize_escape-0.0.3.dist-info/top_level.txt
flask_sanitize_escape-0.0.3.dist-info/RECORD
