Metadata-Version: 2.1
Name: flask-sanitize-escape
Version: 0.0.3
Summary: Sanitization functions for Flask backend input to prevent XSS, RCE, SQLi and many others
Home-page: https://github.com/mayur19/flask-sanitize-escape
Author: Mayur Dusane
Author-email: mayurdusane1@gmail.com
Classifier: Intended Audience :: Developers
Classifier: License :: OSI Approved :: MIT License
Classifier: Programming Language :: Python :: 3
License-File: LICENSE
Requires-Dist: Flask
